CiteSoft/CiteSoft_py.py
CiteSoft/InternalTests.py
CiteSoft/__init__.py
citesoft-0.3.9.data/data/LICENSE.txt
citesoft-0.3.9.data/data/README.md
citesoft-0.3.9.dist-info/LICENSE.txt
citesoft-0.3.9.dist-info/METADATA
citesoft-0.3.9.dist-info/WHEEL
citesoft-0.3.9.dist-info/top_level.txt
citesoft-0.3.9.dist-info/RECORD
