Metadata-Version: 2.2
Name: CiteSoft
Version: 0.3.9
Summary: This is a python implementation of CiteSoft. CiteSoft is a plain text standard consisting of a format and a protocol that exports the citations for the  end-users for whichever softwares they have used. CiteSoft has been designed so that software dev-users can rely upon it regardless of coding language or platform, and even for cases where multiple codes are working in a coupled manner..
Home-page: https://github.com/AdityaSavara/CiteSoft_py
Author: Aditya Savara
Author-email: AditySavara2008@u.northwestern.edu
License: BSD-3-Clause
Classifier: License :: OSI Approved :: BSD License
Classifier: Programming Language :: Python
Classifier: Programming Language :: Python :: 3
Classifier: Programming Language :: Python :: 3.6
Classifier: Programming Language :: Python :: Implementation :: CPython
Classifier: Programming Language :: Python :: Implementation :: PyPy
Requires-Python: >=3.0.0
License-File: LICENSE.txt
Requires-Dist: semantic_version
Requires-Dist: PyYAML
Dynamic: author
Dynamic: author-email
Dynamic: classifier
Dynamic: description
Dynamic: description-content-type
Dynamic: home-page
Dynamic: license
Dynamic: requires-dist
Dynamic: requires-python
Dynamic: summary
